{
  "start":44109,
  "end":44450,
  "label":"SENT",
  "type":"sent",
  "text":"And whenever I went to court, even though I had already told that\n to my dad, I still tried to fight for me being there, I talked to the judge\n and the judge told me, \u201cYou have a criminal charge in the United States and\n you're considered a threat, you're considered a criminal and you're\n considered a threat to the safety of our citizens.\u201d",
  "id":"b3728d65-cf2b-4869-a9d7-e3200c83b3d0",
  "params":{
    "id":"b3728d65-cf2b-4869-a9d7-e3200c83b3d0",
    "class":"anno"
  },
  "name":"Angelo"
}