{
  "start":33649,
  "end":33924,
  "label":"SENT",
  "type":"sent",
  "text":"Different things because right\n   here to live in the States, you either have to be a political asshole, I'm\n   sorry, or somebody that does things that they're not supposed to do.\n   There's a saying here that says, he who doesn't swindle or do something\n   doesn't advance.",
  "id":"b84c3488-39b4-4a8f-90ec-26ed07e9b9ab",
  "params":{
    "id":"b84c3488-39b4-4a8f-90ec-26ed07e9b9ab",
    "class":"anno"
  },
  "name":"Hugo"
}