{
  "start":59039,
  "end":59375,
  "label":"SENT",
  "type":"sent",
  "text":"In a way it was a blessing\n     that there was nothing there for me to enjoy because that just made me\n     more hungry in the sense that it made me more hungry for success and\n     more hungry to have my own back and to scratch my own back and to be\n     more self-reliant and have that self-resiliency to seek success for\n     myself.",
  "id":"ea365491-d507-4999-8341-936f641cd675",
  "params":{
    "id":"ea365491-d507-4999-8341-936f641cd675",
    "class":"anno"
  },
  "name":"Cuauht\u00e9moc"
}